lib/commands.py
lib/embed.py
lib/handler.py
lib/utils.py
lib/v.py
lib/webhook.py
lib/resources/AppEmoji.py
lib/resources/Application.py
lib/resources/AutoModeration.py
lib/resources/Channel.py
lib/resources/Components.py
lib/resources/Embed.py
lib/resources/Emoji.py
lib/resources/Entitlements.py
lib/resources/Guild.py
lib/resources/Invite.py
lib/resources/Message.py
lib/resources/Mod.py
lib/resources/Poll.py
lib/resources/Webhook.py
IntegraCord-0.1.1.dist-info/METADATA
IntegraCord-0.1.1.dist-info/WHEEL
IntegraCord-0.1.1.dist-info/top_level.txt
IntegraCord-0.1.1.dist-info/RECORD
