Metadata-Version: 2.1
Name: IntegraCord
Version: 0.1.1
Summary: IntegraCord that allows you to connect to the application as a 'Webhook' without connecting to the Discord gateway.
Author-email: Paweł Brzyś <m@pawelb.xyz>
Requires-Dist: aiohttp
Requires-Dist: fastapi
Requires-Dist: python-dotenv
Requires-Dist: PyNaCl
Requires-Dist: uvicorn
